odoo/addons/hr_timesheet_report_rounded/README.rst
odoo/addons/hr_timesheet_report_rounded/__init__.py
odoo/addons/hr_timesheet_report_rounded/__manifest__.py
odoo/addons/hr_timesheet_report_rounded/i18n/hr_timesheet_report_rounded.pot
odoo/addons/hr_timesheet_report_rounded/i18n/it.po
odoo/addons/hr_timesheet_report_rounded/readme/CONFIGURE.md
odoo/addons/hr_timesheet_report_rounded/readme/CONTEXT.md
odoo/addons/hr_timesheet_report_rounded/readme/CONTRIBUTORS.md
odoo/addons/hr_timesheet_report_rounded/readme/DESCRIPTION.md
odoo/addons/hr_timesheet_report_rounded/readme/USAGE.md
odoo/addons/hr_timesheet_report_rounded/report/__init__.py
odoo/addons/hr_timesheet_report_rounded/report/hr_timesheet_report.py
odoo/addons/hr_timesheet_report_rounded/static/description/icon.png
odoo/addons/hr_timesheet_report_rounded/static/description/index.html
odoo/addons/hr_timesheet_report_rounded/tests/__init__.py
odoo/addons/hr_timesheet_report_rounded/tests/test_report.py
odoo_addon_hr_timesheet_report_rounded-16.0.1.0.0.5.dist-info/METADATA
odoo_addon_hr_timesheet_report_rounded-16.0.1.0.0.5.dist-info/WHEEL
odoo_addon_hr_timesheet_report_rounded-16.0.1.0.0.5.dist-info/top_level.txt
odoo_addon_hr_timesheet_report_rounded-16.0.1.0.0.5.dist-info/RECORD
