Metadata-Version: 2.1
Name: odoo-addon-hr_timesheet_report_rounded
Version: 16.0.1.0.0.5
Summary: Show rounded time in the Timesheet Reports
Home-page: https://github.com/OCA/timesheet
Author: Cetmix, Odoo Community Association (OCA)
Author-email: support@odoo-community.org
License: AGPL-3
Classifier: Programming Language :: Python
Classifier: Framework :: Odoo
Classifier: Framework :: Odoo :: 16.0
Classifier: License :: OSI Approved :: GNU Affero General Public License v3
Requires-Python: >=3.10
Requires-Dist: odoo-addon-hr-timesheet-report<16.1dev,>=16.0dev
Requires-Dist: odoo-addon-sale-timesheet-rounded<16.1dev,>=16.0dev
Requires-Dist: odoo<16.1dev,>=16.0a
